{
  "kind": "collectionType",
  "collectionName": "pages",
  "info": {
    "singularName": "page",
    "pluralName": "pages",
    "displayName": "Page",
    "description": "Flexible page collection with dynamic fields"
  },
  "options": {
    "draftAndPublish": true
  },
  "pluginOptions": {},
  "attributes": {
    "title": {
      "type": "string",
      "required": true
    },
    "slug": {
      "type": "uid",
      "targetField": "title",
      "required": true
    },
    "sections": {
      "type": "component",
      "repeatable": true,
      "component": "section.section"
    }
  }
}
